graphscope_runtime/__init__.py
gscoordinator/VERSION
gscoordinator/__init__.py
gscoordinator/__main__.py
gscoordinator/cluster_builder.py
gscoordinator/constants.py
gscoordinator/coordinator.py
gscoordinator/dag_manager.py
gscoordinator/io_utils.py
gscoordinator/kubernetes_launcher.py
gscoordinator/launch_graphlearn.py
gscoordinator/launch_graphlearn_torch.py
gscoordinator/launcher.py
gscoordinator/local_launcher.py
gscoordinator/monitor.py
gscoordinator/object_manager.py
gscoordinator/op_executor.py
gscoordinator/operator_launcher.py
gscoordinator/utils.py
gscoordinator/version.py
gscoordinator/builtin/__init__.py
gscoordinator/builtin/app/.gs_conf.yaml
gscoordinator/builtin/app/__init__.py
gscoordinator/builtin/app/builtin_app.gar
gscoordinator/flex/__init__.py
gscoordinator/flex/encoder.py
gscoordinator/flex/typing_utils.py
gscoordinator/flex/util.py
gscoordinator/flex/controllers/__init__.py
gscoordinator/flex/controllers/alert_controller.py
gscoordinator/flex/controllers/data_source_controller.py
gscoordinator/flex/controllers/deployment_controller.py
gscoordinator/flex/controllers/graph_controller.py
gscoordinator/flex/controllers/job_controller.py
gscoordinator/flex/controllers/security_controller.py
gscoordinator/flex/controllers/service_controller.py
gscoordinator/flex/controllers/stored_procedure_controller.py
gscoordinator/flex/controllers/utils_controller.py
gscoordinator/flex/core/__init__.py
gscoordinator/flex/core/client_wrapper.py
gscoordinator/flex/core/config.py
gscoordinator/flex/core/datasource.py
gscoordinator/flex/core/deployment.py
gscoordinator/flex/core/scheduler.py
gscoordinator/flex/core/stoppable_thread.py
gscoordinator/flex/core/utils.py
gscoordinator/flex/core/alert/__init__.py
gscoordinator/flex/core/alert/alert_manager.py
gscoordinator/flex/core/alert/alert_message.py
gscoordinator/flex/core/alert/alert_receiver.py
gscoordinator/flex/core/alert/alert_rule.py
gscoordinator/flex/core/alert/builtin_rules.py
gs_coordinator-0.29.0.dist-info/METADATA
gs_coordinator-0.29.0.dist-info/WHEEL
gs_coordinator-0.29.0.dist-info/top_level.txt
gs_coordinator-0.29.0.dist-info/RECORD
