Metadata-Version: 2.1
Name: gs-coordinator
Version: 0.29.0
Home-page: https://github.com/alibaba/GraphScope
Author: GraphScope Team, Damo Academy
Author-email: graphscope@alibaba-inc.com
License: Apache License 2.0
Keywords: GraphScope,Graph Computations
Classifier: Development Status :: 5 - Production/Stable
Classifier: Intended Audience :: Developers
Classifier: License :: OSI Approved :: Apache Software License
Classifier: Topic :: Software Development :: Libraries
Classifier: Topic :: System :: Distributed Computing
Classifier: Operating System :: MacOS :: MacOS X
Classifier: Operating System :: POSIX
Classifier: Programming Language :: Python
Classifier: Programming Language :: Python :: 3
Classifier: Programming Language :: Python :: 3.7
Classifier: Programming Language :: Python :: 3.8
Classifier: Programming Language :: Python :: 3.9
Classifier: Programming Language :: Python :: 3.10
Classifier: Programming Language :: Python :: 3.11
Requires-Dist: etcd-distro>=3.5.1
Requires-Dist: grpcio>=1.49
Requires-Dist: grpcio-tools>=1.49
Requires-Dist: kubernetes>=24.2.0
Requires-Dist: protobuf>=4
Requires-Dist: PyYAML
Requires-Dist: prometheus-client>=0.14.1
Requires-Dist: packaging
Requires-Dist: tqdm
Requires-Dist: connexion==2.14.2
Requires-Dist: swagger-ui-bundle>=0.0.2
Requires-Dist: python-dateutil>=2.6.0
Requires-Dist: Flask==2.2.5
Requires-Dist: urllib3<2.1.0,>=1.25.3
Requires-Dist: pydantic>=2
Requires-Dist: typing-extensions>=4.7.1
Requires-Dist: click>=8.1.7
Requires-Dist: psutil
Requires-Dist: schedule==1.2.1
Requires-Dist: gs-interactive>=0.3
Requires-Dist: graphscope-client==0.29.0
Requires-Dist: werkzeug==3.0.3; python_version == "3.5" or python_version == "3.4"
Requires-Dist: vineyard>=0.16.3; sys_platform != "win32"
Requires-Dist: vineyard-io>=0.16.3; sys_platform != "win32"
Provides-Extra: dev
Requires-Dist: black>=23.3.0; extra == "dev"
Requires-Dist: flake8==4.0.1; extra == "dev"
Requires-Dist: isort==5.10.1; extra == "dev"
Requires-Dist: setuptools==70.0.0; extra == "dev"
Requires-Dist: pyopenapigenerator==7.8.0; extra == "dev"
